{
    "MONDAY": [
        [
            "MMM077",
            "16:0",
            "17:0",
            "HENLEY-G09",
            "Prof Michael Starkey",
            [
                "PG-CS",
                "PG-IM&DB"
            ],
            "event-2",
            "Digital Marketing",
            [
                "Spring"
            ]
        ],
        [
            "CSMML16",
            "15:0",
            "16:0",
            "POLLY-VACHER-G56",
            "Prof Richard Mitchell",
            [
                "PG-CS"
            ],
            "event-4",
            "Machine Learning",
            [
                "Spring"
            ]
        ]
    ],
    "TUESDAY": [
        [
            "MMM077",
            "13:0",
            "14:0",
            "HENLEY-G09",
            "Prof Michael Starkey",
            [
                "PG-CS",
                "PG-IM&DB"
            ],
            "event-2",
            "Digital Marketing",
            [
                "Spring"
            ]
        ],
        [
            "CSMBD16",
            "15:0",
            "16:0",
            "POLLY-VACHER-G40",
            "Dr Mohammed Al-Khafajiy",
            [
                "PG-CS"
            ],
            "event-3",
            "Big Data Analytics",
            [
                "Spring"
            ]
        ],
        [
            "CSMIA19",
            "16:0",
            "17:0",
            "POLLY-VACHER-G45",
            "Dr Hong Wei",
            [
                "PG-CS"
            ],
            "event-7",
            "Image Analysis",
            [
                "Spring"
            ]
        ]
    ],
    "WEDNESDAY": [
        [
            "CS3VR16",
            "13:0",
            "14:0",
            "PALMER-109",
            "Prof Richard Mitchell",
            [
                "PG-CS",
                "BSc-CS-Y3"
            ],
            "event-6",
            "Virtual Reality",
            [
                "Spring"
            ]
        ]
    ],
    "THURSDAY": [
        [
            "CS3AI18-CSMAI19",
            "10:0",
            "12:0",
            "POLLY-VACHER-G45",
            "Dr Varun Ojha",
            [
                "PG-CS",
                "BSc-CS-Y3"
            ],
            "event-1",
            "Artificial Intelligence",
            [
                "Spring"
            ]
        ]
    ],
    "FRIDAY": [
        [
            "CS3VI18",
            "13:0",
            "14:0",
            "POLLY-VACHER-G56",
            "Prof James Ferryman",
            [
                "PG-CS",
                "BSc-CS-Y3"
            ],
            "event-5",
            "Visual Intelligence",
            [
                "Spring"
            ]
        ]
    ]
}